<annotation>
	<folder>train</folder>
	<filename>194.jpg</filename>
	<path>C:\Users\ASUS-Laptop\Desktop\train\194.jpg</path>
	<source>
		<database>Unknown</database>
	</source>
	<size>
		<width>320</width>
		<height>240</height>
		<depth>3</depth>
	</size>
	<segmented>0</segmented>
	<object>
		<name>bottle</name>
		<pose>Unspecified</pose>
		<truncated>0</truncated>
		<difficult>0</difficult>
		<bndbox>
			<xmin>105</xmin>
			<ymin>34</ymin>
			<xmax>295</xmax>
			<ymax>98</ymax>
		</bndbox>
	</object>
	<object>
		<name>paper</name>
		<pose>Unspecified</pose>
		<truncated>0</truncated>
		<difficult>0</difficult>
		<bndbox>
			<xmin>10</xmin>
			<ymin>125</ymin>
			<xmax>73</xmax>
			<ymax>189</ymax>
		</bndbox>
	</object>
	<object>
		<name>plastic-bag</name>
		<pose>Unspecified</pose>
		<truncated>0</truncated>
		<difficult>0</difficult>
		<bndbox>
			<xmin>153</xmin>
			<ymin>81</ymin>
			<xmax>309</xmax>
			<ymax>206</ymax>
		</bndbox>
	</object>
	<object>
		<name>paper</name>
		<pose>Unspecified</pose>
		<truncated>0</truncated>
		<difficult>0</difficult>
		<bndbox>
			<xmin>119</xmin>
			<ymin>139</ymin>
			<xmax>148</xmax>
			<ymax>177</ymax>
		</bndbox>
	</object>
</annotation>
